rsnchat/__init__.py
rsnchat/main.py
rsnchat-4.0.0.dist-info/METADATA
rsnchat-4.0.0.dist-info/WHEEL
rsnchat-4.0.0.dist-info/top_level.txt
rsnchat-4.0.0.dist-info/RECORD
