Metadata-Version: 2.1
Name: rsnchat
Version: 4.0.0
Summary: A package for interacting with GPT4-based chat services, OpenChat, Bard, Gemini, LlaMa, Mixtral, Prodia, Kandinsky, Absolutebeauty, Sdxl, Dalle and AI Icon
Home-page: UNKNOWN
Author: rnilaweera
Author-email: stacxdev@gmail.com
License: UNKNOWN
Keywords: python,first package
Platform: UNKNOWN
Requires-Dist: requests
